pyzenodo3/__init__.py
pyzenodo3/upload.py
pyzenodo3-0.1.1.dist-info/LICENSE.txt
pyzenodo3-0.1.1.dist-info/METADATA
pyzenodo3-0.1.1.dist-info/RECORD
pyzenodo3-0.1.1.dist-info/WHEEL
pyzenodo3-0.1.1.dist-info/top_level.txt
