Metadata-Version: 2.1
Name: pyzenodo3
Version: 0.1.1
Summary: Pure Python 3 wrapper for the Zenodo REST API
Home-page: UNKNOWN
Author: Michael Hirsch, Tom Klaver
License: Apache 2.0
Keywords: zenodo,open data
Platform: UNKNOWN
Classifier: Development Status :: 3 - Alpha
Classifier: Environment :: Console
Classifier: Intended Audience :: Developers
Classifier: Operating System :: OS Independent
Classifier: Programming Language :: Python :: 3.6
Classifier: Programming Language :: Python :: 3.7
Classifier: Topic :: Software Development :: Libraries :: Python Modules
Classifier: Topic :: Scientific/Engineering
Requires-Python: >=3.6
Provides-Extra: tests
Requires-Dist: requests
Requires-Dist: Beautifulsoup4
Provides-Extra: tests
Requires-Dist: pytest; extra == 'tests'
Requires-Dist: pytest-cov; extra == 'tests'
Requires-Dist: coveralls; extra == 'tests'
Requires-Dist: flake8; extra == 'tests'
Requires-Dist: mypy; extra == 'tests'
